LICENSE
MANIFEST.in
README.rst
setup.py
asmbench/__init__.py
asmbench/__main__.py
asmbench/bench.py
asmbench/oldjit.py
asmbench/op.py
asmbench/sc18src.py
asmbench.egg-info/PKG-INFO
asmbench.egg-info/SOURCES.txt
asmbench.egg-info/dependency_links.txt
asmbench.egg-info/requires.txt
asmbench.egg-info/top_level.txt