Metadata-Version: 1.0
Name: asmbench
Version: 0.1.2
Summary: A Benchmark Toolkit for Assembly Instructions Using the LLVM JIT
Home-page: https://github.com/RRZE-HPC/asmbench
Author: Julian Hammer
Author-email: julian.hammer@fau.de
License: AGPLv3
Platform: UNKNOWN
